pontaria/app.py
pontaria/auth.py
pontaria/date_utils.py
pontaria-0.1.5.dist-info/METADATA
pontaria-0.1.5.dist-info/WHEEL
pontaria-0.1.5.dist-info/entry_points.txt
pontaria-0.1.5.dist-info/top_level.txt
pontaria-0.1.5.dist-info/RECORD
