Metadata-Version: 2.1
Name: pontaria
Version: 0.1.5
Summary: A time monitoring utility for Birdie's tasks
Home-page: UNKNOWN
Author: Henrique Cunha
Author-email: henrique.cunha@birdie.ai
License: UNKNOWN
Platform: UNKNOWN
Requires-Dist: arrow
Requires-Dist: gspread
Requires-Dist: google-api-python-client
Requires-Dist: google-auth-httplib2
Requires-Dist: google-auth-oauthlib
